{"username": "juniorbachchan", "words": {"thank": 384, "birthday": 113, "ruth": 82, "love": 63, "day": 46, "luck": 38, "brother": 36, "year": 36, "done": 33, "happy": 32, "gayatri": 30, "well": 30, "team": 27, "see": 26, "friend": 25, "bunty": 24, "good": 23, "let": 23, "earth": 23, "today": 22, "come": 21, "yes": 21, "support": 21, "believe": 19, "time": 18, "work": 18, "lot": 17, "win": 16, "watch": 16, "looking": 15, "wait": 15, "release": 15, "film": 15, "season": 14, "buddy": 14, "know": 14, "hope": 14, "power": 13, "please": 13, "sir": 13, "keep": 13, "always": 12, "look": 12, "get": 12, "tania": 12, "god": 11, "wishing": 11, "rohan": 10, "best": 10, "try": 10, "think": 10, "man": 10, "full": 9, "winning": 9, "show": 9, "stay": 9, "bless": 9, "big": 9, "mon": 9, "game": 9, "welcome": 9, "sport": 9, "way": 9, "news": 9, "making": 8, "people": 8, "many": 8, "football": 8, "need": 8, "new": 8, "night": 8, "life": 8, "kind": 8, "uncle": 8, "hate": 8, "tonight": 7, "thanks": 7, "raj": 7, "coming": 7, "hard": 7, "made": 7, "respect": 7, "wow": 7, "help": 7, "hey": 7, "angel": 7, "great": 7, "tomorrow": 7, "dream": 7, "listen": 7, "hug": 7, "tweet": 7, "legend": 6, "blessed": 6, "debut": 6, "song": 6, "thing": 6, "world": 6, "watching": 6, "trailer": 6, "question": 6, "one": 6, "trying": 6, "going": 6, "dear": 6, "sentinel": 6, "part": 5, "journey": 5, "breathe": 5, "absolutely": 5, "morning": 5, "match": 5, "family": 5, "wish": 5, "remember": 5, "got": 5, "beautiful": 5, "video": 5, "hear": 5, "continue": 5, "make": 5, "truth": 5, "smiling": 5, "check": 5, "captain": 5, "agree": 5, "vote": 4, "may": 4, "outstanding": 4, "home": 4, "action": 4, "sandy": 4, "anna": 4, "seeing": 4, "sign": 4, "play": 4, "pleasure": 4, "future": 4, "blue": 4, "enjoy": 4, "boy": 4, "sister": 4, "call": 4, "take": 4, "fan": 4, "stop": 4, "buy": 4, "seen": 4, "player": 4, "doctor": 4, "country": 4, "singh": 4, "attack": 4, "something": 4, "would": 4, "feel": 4, "meant": 4, "mind": 4, "start": 4, "amen": 4, "album": 4, "dada": 3, "forget": 3, "want": 3, "cricket": 3, "cool": 3, "director": 3, "give": 3, "live": 3, "stadium": 3, "book": 3, "link": 3, "line": 3, "retirement": 3, "cup": 3, "hour": 3, "right": 3, "anniversary": 3, "anything": 3, "much": 3, "golden": 3, "shooting": 3, "filled": 3, "tara": 3, "face": 3, "chance": 3, "taken": 3, "opportunity": 3, "chin": 3, "becomes": 3, "unit": 3, "becoming": 3, "young": 3, "join": 3, "running": 3, "working": 3, "back": 3, "stage": 3, "advice": 3, "amazing": 3, "queen": 3, "saw": 3, "count": 3, "care": 3, "truly": 3, "baby": 3, "baba": 3, "naik": 3, "champ": 3, "khan": 3, "word": 3, "read": 3, "star": 3, "hain": 3, "track": 3, "experience": 2, "bridge": 2, "living": 2, "cause": 2, "put": 2, "pink": 2, "jam": 2, "studio": 2, "rest": 2, "went": 2, "son": 2, "catch": 2, "papa": 2, "somebody": 2, "leadership": 2, "never": 2, "wake": 2, "taught": 2, "guru": 2, "passion": 2, "actor": 2, "guy": 2, "mate": 2, "zee": 2, "really": 2, "crew": 2, "premiere": 2, "lucky": 2, "final": 2, "half": 2, "giving": 2, "child": 2, "husband": 2, "wife": 2, "election": 2, "run": 2, "must": 2, "learn": 2, "fun": 2, "stuck": 2, "wonderful": 2, "group": 2, "round": 2, "raider": 2, "sri": 2, "shah": 2, "raid": 2, "dad": 2, "advance": 2, "getting": 2, "sorry": 2, "awesome": 2, "post": 2, "supporter": 2, "minister": 2, "thought": 2, "traffic": 2, "mission": 2, "towards": 2, "twitter": 2, "hell": 2, "guessing": 2, "chicken": 2, "club": 2, "beginning": 2, "nep": 2, "matter": 2, "movie": 2, "gang": 2, "cinema": 2, "next": 2, "directed": 2, "picture": 2, "father": 2, "brave": 2, "head": 2, "childhood": 2, "car": 2, "left": 2, "send": 2, "exactly": 2, "appreciate": 2, "reason": 2, "superb": 2, "yesterday": 2, "light": 2, "feeling": 2, "celebrate": 2, "inspiration": 2, "biggest": 2, "ani": 2, "focus": 2, "dinner": 2, "age": 2, "find": 2, "deserved": 2, "talk": 2, "represent": 2, "mat": 2, "industry": 2, "happiness": 2, "nobody": 2, "ride": 2, "begin": 2, "spend": 2, "health": 2, "jungle": 2, "photo": 2, "story": 2, "career": 2, "lady": 2, "genius": 2, "poster": 2, "phew": 2, "bye": 2, "become": 2, "learning": 2, "article": 2, "bring": 2, "insanity": 2, "stall": 2, "dignity": 2, "heart": 2, "message": 2, "junior": 2, "prime": 2, "gill": 2, "first": 2, "say": 2, "hone": 2, "acting": 2, "divine": 2, "collected": 2, "tragic": 2, "happening": 2, "deserve": 2, "till": 2, "choice": 2, "consider": 2, "mine": 2, "hopefully": 2, "knock": 2, "park": 2, "eros": 2, "walk": 2, "belated": 2, "understand": 2, "champion": 2, "sleeping": 2, "considered": 2, "parody": 2, "account": 2, "sauce": 1, "took": 1, "commitment": 1, "backing": 1, "equation": 1, "follow": 1, "display": 1, "brilliance": 1, "record": 1, "perspective": 1, "scoring": 1, "return": 1, "city": 1, "buzzing": 1, "joy": 1, "gym": 1, "apart": 1, "hit": 1, "turf": 1, "fortress": 1, "grab": 1, "bos": 1, "hoti": 1, "bull": 1, "remain": 1, "sportsman": 1, "rise": 1, "hearing": 1, "speechless": 1, "campaign": 1, "camp": 1, "bead": 1, "sweat": 1, "carry": 1, "band": 1, "golf": 1, "midst": 1, "drawn": 1, "lene": 1, "swash": 1, "entrepreneur": 1, "microscope": 1, "discerning": 1, "premium": 1, "race": 1, "backwards": 1, "competition": 1, "taut": 1, "edge": 1, "seat": 1, "thriller": 1, "cast": 1, "cooler": 1, "triangle": 1, "confusion": 1, "television": 1, "apparently": 1, "mila": 1, "tabu": 1, "consumption": 1, "happiest": 1, "girl": 1, "premier": 1, "league": 1, "winner": 1, "couple": 1, "succession": 1, "arm": 1, "err": 1, "calm": 1, "forgetting": 1, "posting": 1, "supporting": 1, "remind": 1, "tested": 1, "prevent": 1, "nominate": 1, "movement": 1, "visit": 1, "minor": 1, "tha": 1, "fact": 1, "exercise": 1, "blood": 1, "clock": 1, "ticking": 1, "contribute": 1, "blank": 1, "path": 1, "doc": 1, "feather": 1, "jay": 1, "bleeding": 1, "increase": 1, "peace": 1, "assistance": 1, "seeking": 1, "clarification": 1, "order": 1, "annual": 1, "national": 1, "youth": 1, "workshop": 1, "interact": 1, "tera": 1, "chal": 1, "goa": 1, "banana": 1, "single": 1, "tired": 1, "beauty": 1, "onto": 1, "history": 1, "color": 1, "addition": 1, "wealth": 1, "strength": 1, "defence": 1, "rounder": 1, "dong": 1, "kim": 1, "auction": 1, "nana": 1, "pick": 1, "pavan": 1, "die": 1, "everything": 1, "choose": 1, "monkey": 1, "suit": 1, "actually": 1, "roi": 1, "grosser": 1, "united": 1, "petition": 1, "finance": 1, "remove": 1, "used": 1, "wit": 1, "courtesy": 1, "amar": 1, "inflation": 1, "ticket": 1, "strange": 1, "snob": 1, "road": 1, "beta": 1, "shoot": 1, "avoid": 1, "diving": 1, "protect": 1, "raw": 1, "moving": 1, "someone": 1, "apartment": 1, "floor": 1, "squad": 1, "moon": 1, "huge": 1, "travelled": 1, "butter": 1, "beware": 1, "enjoying": 1, "even": 1, "feed": 1, "qualifier": 1, "broken": 1, "version": 1, "awesomeness": 1, "tried": 1, "pitch": 1, "habit": 1, "suggest": 1, "everyone": 1, "manner": 1, "job": 1, "prepared": 1, "ended": 1, "slept": 1, "counting": 1, "loop": 1, "bond": 1, "coop": 1, "topical": 1, "teaser": 1, "cakewalk": 1, "chose": 1, "design": 1, "room": 1, "terror": 1, "memory": 1, "lifetime": 1, "personnel": 1, "condemn": 1, "powered": 1, "par": 1, "trapped": 1, "web": 1, "evidently": 1, "nothing": 1, "doubtful": 1, "observation": 1, "pose": 1, "kyle": 1, "open": 1, "chaos": 1, "ready": 1, "born": 1, "finally": 1, "told": 1, "corner": 1, "repay": 1, "set": 1, "given": 1, "faffy": 1, "aho": 1, "mib": 1, "little": 1, "surprise": 1, "drove": 1, "feast": 1, "forever": 1, "ditto": 1, "marzipan": 1, "plan": 1, "encouragement": 1, "village": 1, "side": 1, "dev": 1, "indoors": 1, "warm": 1, "stylist": 1, "designer": 1, "explain": 1, "elaborate": 1, "hurt": 1, "suffer": 1, "lesson": 1, "grow": 1, "every": 1, "contender": 1, "rocky": 1, "balboa": 1, "nice": 1, "jacket": 1, "tennis": 1, "tour": 1, "josh": 1, "fight": 1, "efficacy": 1, "language": 1, "overcome": 1, "lead": 1, "situation": 1, "smile": 1, "victory": 1, "calling": 1, "gathering": 1, "importance": 1, "connection": 1, "body": 1, "fire": 1, "passing": 1, "fortune": 1, "institution": 1, "person": 1, "merry": 1, "zero": 1, "sense": 1, "everlasting": 1, "legacy": 1, "break": 1, "button": 1, "excited": 1, "session": 1, "tradition": 1, "step": 1, "missing": 1, "happen": 1, "announce": 1, "produced": 1, "sideline": 1, "leg": 1, "together": 1, "pray": 1, "stream": 1, "case": 1, "push": 1, "shove": 1, "save": 1, "streaming": 1, "delighted": 1, "ala": 1, "polite": 1, "reminder": 1, "screen": 1, "roar": 1, "shave": 1, "baloo": 1, "promotion": 1, "spoken": 1, "whatever": 1, "place": 1, "birth": 1, "daughter": 1, "freak": 1, "boom": 1, "fantastic": 1, "launch": 1, "telling": 1, "success": 1, "fasting": 1, "wave": 1, "devoted": 1, "helping": 1, "teaching": 1, "oho": 1, "koi": 1, "storm": 1, "worker": 1, "drag": 1, "credit": 1, "go": 1, "build": 1, "momentum": 1, "spent": 1, "guess": 1, "tune": 1, "ist": 1, "paint": 1, "cheer": 1, "newspaper": 1, "jersey": 1, "fused": 1, "judge": 1, "touched": 1, "promise": 1, "wali": 1, "miss": 1, "register": 1, "end": 1, "stree": 1, "analyst": 1, "coz": 1, "said": 1, "information": 1, "professional": 1, "expect": 1, "study": 1, "proclaiming": 1, "economics": 1, "embarrass": 1, "clap": 1, "growing": 1, "name": 1, "panther": 1, "adorable": 1, "write": 1, "author": 1, "answer": 1, "quirky": 1, "intimate": 1, "novel": 1, "dan": 1, "sire": 1, "sung": 1, "ram": 1, "thug": 1, "jordan": 1, "lie": 1, "hair": 1, "prince": 1, "duality": 1, "rishi": 1, "type": 1, "cover": 1, "sit": 1, "chat": 1, "carpet": 1, "preorder": 1, "tell": 1, "taking": 1, "streep": 1, "award": 1, "excellence": 1, "congratulatory": 1, "theta": 1, "lovely": 1, "meeting": 1, "resist": 1, "warn": 1, "aka": 1, "dancing": 1, "change": 1, "mane": 1, "tiff": 1, "net": 1, "performance": 1, "food": 1, "heartbreak": 1, "august": 1, "desire": 1, "kit": 1, "spread": 1, "awareness": 1, "entry": 1, "arsenal": 1, "donate": 1, "maximum": 1, "phase": 1, "distributed": 1, "lyrical": 1, "student": 1, "concern": 1, "independence": 1, "period": 1, "voice": 1, "air": 1, "venture": 1, "niece": 1, "model": 1, "move": 1, "dance": 1, "ask": 1, "decision": 1, "drop": 1, "affected": 1, "manager": 1, "unending": 1, "dop": 1, "rab": 1, "awkward": 1, "audio": 1, "outdoor": 1, "came": 1, "stuff": 1, "gon": 1, "triple": 1, "lazy": 1, "cap": 1, "inspiring": 1, "leaf": 1, "lump": 1, "throat": 1, "waiting": 1, "explode": 1, "date": 1, "fought": 1, "pay": 1, "wasabi": 1, "bill": 1, "laughing": 1, "slip": 1, "refrain": 1, "intent": 1, "fly": 1, "disappoint": 1, "karo": 1, "hum": 1, "sab": 1, "turn": 1, "laughter": 1, "worked": 1, "entertaining": 1, "hence": 1, "silence": 1, "gold": 1, "level": 1, "da": 1, "beat": 1, "foot": 1, "evil": 1, "dare": 1, "crazy": 1, "brazil": 1, "sadly": 1, "gaby": 1, "possible": 1, "mouth": 1, "shut": 1, "eat": 1, "junk": 1, "beast": 1, "doubt": 1, "conversation": 1, "keeping": 1, "tone": 1, "convince": 1, "sure": 1, "defense": 1, "wrote": 1, "trouble": 1, "ever": 1, "tagged": 1, "mail": 1, "surely": 1, "discretion": 1, "cue": 1, "slim": 1, "unbelievable": 1, "insane": 1, "typical": 1, "faith": 1, "usual": 1, "pushing": 1, "russia": 1, "immense": 1, "effort": 1, "attract": 1, "classified": 1, "priority": 1, "community": 1, "association": 1, "decided": 1, "beating": 1, "hind": 1, "zombie": 1, "bump": 1}, "emojis": {"microscope": {"emoji": "microscope", "score": 1.0000001192092896}, "newspaper": {"emoji": "newspaper", "score": 1.0000001192092896}, "watch": {"emoji": "watch", "score": 1.0}, "man": {"emoji": "man", "score": 1.0}, "family": {"emoji": "family", "score": 1.0}, "cricket": {"emoji": "cricket", "score": 1.0}, "stadium": {"emoji": "stadium", "score": 1.0}, "link": {"emoji": "link", "score": 1.0}, "baby": {"emoji": "baby", "score": 1.0}, "mate": {"emoji": "mate", "score": 1.0}, "child": {"emoji": "child", "score": 1.0}, "cinema": {"emoji": "cinema", "score": 1.0}, "seat": {"emoji": "seat", "score": 1.0}, "television": {"emoji": "television", "score": 1.0}, "banana": {"emoji": "banana", "score": 1.0}, "pick": {"emoji": "pick", "score": 1.0}, "monkey": {"emoji": "monkey", "score": 1.0}, "ticket": {"emoji": "ticket", "score": 1.0}, "butter": {"emoji": "butter", "score": 1.0}, "tennis": {"emoji": "tennis", "score": 1.0}, "fire": {"emoji": "fire", "score": 1.0}, "ram": {"emoji": "ram", "score": 1.0}, "prince": {"emoji": "prince", "score": 1.0}, "mouth": {"emoji": "mouth", "score": 1.0}, "zombie": {"emoji": "zombie", "score": 1.0}, "boy": {"emoji": "boy", "score": 0.9999999403953552}, "chicken": {"emoji": "chicken", "score": 0.9999999403953552}, "girl": {"emoji": "girl", "score": 0.9999999403953552}, "person": {"emoji": "person", "score": 0.9999999403953552}, "star": {"emoji": "star", "score": 0.9999998807907104}, "leg": {"emoji": "leg", "score": 0.9999998807907104}, "information": {"emoji": "information", "score": 0.9999998807907104}, "foot": {"emoji": "foot", "score": 0.9999998807907104}, "button": {"emoji": "new-button", "score": 0.9082486629486084}, "moon": {"emoji": "new-moon", "score": 0.8842228651046753}, "check": {"emoji": "check-box-with-check", "score": 0.8767729997634888}, "smiling": {"emoji": "smiling-face-with-smiling-eyes", "score": 0.8738672733306885}, "football": {"emoji": "rugby-football", "score": 0.8488445281982422}, "victory": {"emoji": "victory-hand", "score": 0.8446947336196899}, "video": {"emoji": "video-camera", "score": 0.8438701629638672}, "food": {"emoji": "canned-food", "score": 0.8360716104507446}, "net": {"emoji": "goal-net", "score": 0.8360641598701477}, "worker": {"emoji": "construction-worker", "score": 0.8350747227668762}, "sign": {"emoji": "plus-sign", "score": 0.832825243473053}, "judge": {"emoji": "man-judge", "score": 0.8289123773574829}, "student": {"emoji": "man-student", "score": 0.825905442237854}, "birthday": {"emoji": "birthday-cake", "score": 0.822228729724884}, "dancing": {"emoji": "man-dancing", "score": 0.8212810754776001}, "blood": {"emoji": "drop-of-blood", "score": 0.820676326751709}, "tired": {"emoji": "tired-face", "score": 0.8176782131195068}, "angel": {"emoji": "baby-angel", "score": 0.817645251750946}, "post": {"emoji": "post-office", "score": 0.8154590725898743}, "picture": {"emoji": "framed-picture", "score": 0.8152929544448853}, "sleeping": {"emoji": "sleeping-face", "score": 0.8120570182800293}, "shooting": {"emoji": "shooting-star", "score": 0.8109609484672546}, "car": {"emoji": "police-car", "score": 0.8099774718284607}, "entry": {"emoji": "no-entry", "score": 0.8072353005409241}, "clock": {"emoji": "timer-clock", "score": 0.8058184385299683}, "leaf": {"emoji": "maple-leaf", "score": 0.8038483262062073}, "stop": {"emoji": "stop-sign", "score": 0.796007513999939}, "face": {"emoji": "fearful-face", "score": 0.7939836382865906}, "die": {"emoji": "game-die", "score": 0.7922074794769287}, "park": {"emoji": "national-park", "score": 0.7920786142349243}, "question": {"emoji": "question-mark", "score": 0.7892348766326904}, "game": {"emoji": "video-game", "score": 0.7885118722915649}, "heart": {"emoji": "red-heart", "score": 0.7877609729766846}, "hit": {"emoji": "direct-hit", "score": 0.7856829166412354}, "credit": {"emoji": "credit-card", "score": 0.7849405407905579}, "watching": {"emoji": "watch", "score": 0.7835854887962341}, "suit": {"emoji": "club-suit", "score": 0.7735279202461243}, "wave": {"emoji": "water-wave", "score": 0.7718344926834106}, "mail": {"emoji": "e-mail", "score": 0.7712761163711548}, "cup": {"emoji": "cup-with-straw", "score": 0.7686982154846191}, "web": {"emoji": "spider-web", "score": 0.7684663534164429}, "diving": {"emoji": "diving-mask", "score": 0.7655579447746277}, "broken": {"emoji": "broken-heart", "score": 0.7641169428825378}, "one": {"emoji": "one-thirty", "score": 0.7627744674682617}, "movie": {"emoji": "movie-camera", "score": 0.762567400932312}, "arm": {"emoji": "mechanical-arm", "score": 0.7592979669570923}, "open": {"emoji": "open-hands", "score": 0.7546107769012451}, "blue": {"emoji": "blue-circle", "score": 0.7544211149215698}, "film": {"emoji": "film-projector", "score": 0.7541224956512451}, "beating": {"emoji": "beating-heart", "score": 0.7505936622619629}, "book": {"emoji": "open-book", "score": 0.7498846054077148}, "joy": {"emoji": "cat-with-tears-of-joy", "score": 0.7462149858474731}, "cap": {"emoji": "billed-cap", "score": 0.7341303825378418}, "studio": {"emoji": "studio-microphone", "score": 0.7325272560119629}, "sweat": {"emoji": "sweat-droplets", "score": 0.7323960065841675}, "bridge": {"emoji": "bridge-at-night", "score": 0.7306146621704102}, "smile": {"emoji": "cat-with-wry-smile", "score": 0.7284618616104126}, "right": {"emoji": "left-right-arrow", "score": 0.7283711433410645}, "name": {"emoji": "name-badge", "score": 0.727599024772644}, "running": {"emoji": "man-running", "score": 0.7265456318855286}, "reminder": {"emoji": "reminder-ribbon", "score": 0.7216963768005371}, "light": {"emoji": "light-bulb", "score": 0.7118298411369324}, "peace": {"emoji": "peace-symbol", "score": 0.7101051807403564}, "win": {"emoji": "victory-hand", "score": 0.7088594436645508}, "growing": {"emoji": "growing-heart", "score": 0.7082215547561646}, "love": {"emoji": "love-letter", "score": 0.7076706886291504}, "traffic": {"emoji": "vertical-traffic-light", "score": 0.7073163986206055}, "queen": {"emoji": "princess", "score": 0.7070531845092773}, "golf": {"emoji": "person-golfing", "score": 0.7018190622329712}, "evil": {"emoji": "see-no-evil-monkey", "score": 0.6994276642799377}, "head": {"emoji": "speaking-head", "score": 0.6965384483337402}, "fortune": {"emoji": "fortune-cookie", "score": 0.6952646970748901}, "track": {"emoji": "railway-track", "score": 0.69429612159729}, "room": {"emoji": "mens-room", "score": 0.6933736801147461}, "lady": {"emoji": "lady-beetle", "score": 0.6903688907623291}, "dance": {"emoji": "woman-dancing", "score": 0.6853571534156799}, "clap": {"emoji": "clapping-hands", "score": 0.6846178770065308}, "national": {"emoji": "national-park", "score": 0.6827847361564636}, "club": {"emoji": "club-suit", "score": 0.6788320541381836}, "loop": {"emoji": "curly-loop", "score": 0.6667511463165283}, "warn": {"emoji": "warning", "score": 0.6658855080604553}, "someone": {"emoji": "person", "score": 0.6657355427742004}, "apartment": {"emoji": "house", "score": 0.6628996133804321}, "cool": {"emoji": "cool-button", "score": 0.6628749966621399}, "night": {"emoji": "night-with-stars", "score": 0.6584844589233398}, "call": {"emoji": "call-me-hand", "score": 0.6576353907585144}, "triangle": {"emoji": "red-triangle-pointed-up", "score": 0.6575493216514587}, "left": {"emoji": "left-right-arrow", "score": 0.6573630571365356}, "world": {"emoji": "world-map", "score": 0.6565428376197815}, "laughing": {"emoji": "rolling-on-the-floor-laughing", "score": 0.6528129577636719}, "protect": {"emoji": "shield", "score": 0.6524429321289062}, "jacket": {"emoji": "coat", "score": 0.6492949724197388}, "daughter": {"emoji": "girl", "score": 0.6489863991737366}, "couple": {"emoji": "couple-with-heart", "score": 0.6463906764984131}, "walk": {"emoji": "person-walking", "score": 0.6446892023086548}, "place": {"emoji": "place-of-worship", "score": 0.6425546407699585}, "storm": {"emoji": "tornado", "score": 0.6416176557540894}, "drop": {"emoji": "drop-of-blood", "score": 0.6412402987480164}, "full": {"emoji": "full-moon", "score": 0.6385551691055298}, "hearing": {"emoji": "ear-with-hearing-aid", "score": 0.6367064714431763}, "son": {"emoji": "boy", "score": 0.6337764263153076}, "together": {"emoji": "palms-up-together", "score": 0.6333181858062744}, "sport": {"emoji": "sport-utility-vehicle", "score": 0.6327400207519531}, "panther": {"emoji": "tiger", "score": 0.6312947273254395}, "sauce": {"emoji": "custard", "score": 0.6271421909332275}, "back": {"emoji": "back-arrow", "score": 0.6209165453910828}, "type": {"emoji": "b-button-blood-type", "score": 0.6134762763977051}, "floor": {"emoji": "rolling-on-the-floor-laughing", "score": 0.6084661483764648}, "write": {"emoji": "writing-hand", "score": 0.6076998114585876}, "lie": {"emoji": "lying-face", "score": 0.6063346862792969}, "round": {"emoji": "round-pushpin", "score": 0.6060001850128174}, "niece": {"emoji": "old-woman", "score": 0.604297935962677}, "hug": {"emoji": "kiss", "score": 0.6025069355964661}, "anna": {"emoji": "mrs-claus", "score": 0.5991389751434326}, "race": {"emoji": "horse-racing", "score": 0.5959107875823975}, "people": {"emoji": "people-wrestling", "score": 0.5955030918121338}, "actor": {"emoji": "man-singer", "score": 0.5943589806556702}, "rise": {"emoji": "rose", "score": 0.5936158895492554}, "happy": {"emoji": "sad-but-relieved-face", "score": 0.5901215076446533}, "health": {"emoji": "man-health-worker", "score": 0.5896596312522888}, "shave": {"emoji": "shaved-ice", "score": 0.5895823240280151}, "mon": {"emoji": "fleur-de-lis", "score": 0.586524248123169}, "record": {"emoji": "record-button", "score": 0.5859845876693726}, "match": {"emoji": "cricket-game", "score": 0.5831599235534668}, "getting": {"emoji": "person-getting-haircut", "score": 0.5824776291847229}, "pink": {"emoji": "white-flower", "score": 0.5812776684761047}, "register": {"emoji": "registered", "score": 0.5807552337646484}, "chin": {"emoji": "nose", "score": 0.5768921375274658}, "sorry": {"emoji": "sad-but-relieved-face", "score": 0.576383113861084}, "guy": {"emoji": "man-getting-haircut", "score": 0.5762790441513062}, "slept": {"emoji": "sleeping-face", "score": 0.5758758783340454}, "explode": {"emoji": "exploding-head", "score": 0.575491189956665}, "play": {"emoji": "play-button", "score": 0.5744958519935608}, "father": {"emoji": "family", "score": 0.5717043876647949}, "thought": {"emoji": "thought-balloon", "score": 0.5705069899559021}, "beat": {"emoji": "beating-heart", "score": 0.5696597099304199}, "scoring": {"emoji": "musical-score", "score": 0.568719744682312}, "bead": {"emoji": "prayer-beads", "score": 0.5684994459152222}, "band": {"emoji": "guitar", "score": 0.5669187307357788}, "first": {"emoji": "first-quarter-moon", "score": 0.5662580132484436}, "marzipan": {"emoji": "custard", "score": 0.5656149387359619}, "jersey": {"emoji": "running-shirt", "score": 0.5654147267341614}, "laughter": {"emoji": "cat-with-tears-of-joy", "score": 0.5648735761642456}, "end": {"emoji": "end-arrow", "score": 0.5633747577667236}, "cover": {"emoji": "notebook-with-decorative-cover", "score": 0.5633113384246826}, "birth": {"emoji": "baby", "score": 0.5630236268043518}, "hey": {"emoji": "ok-hand", "score": 0.562850832939148}, "home": {"emoji": "house", "score": 0.5617802143096924}, "wife": {"emoji": "family", "score": 0.5601866841316223}, "da": {"emoji": "fleur-de-lis", "score": 0.5595588684082031}, "fortress": {"emoji": "castle", "score": 0.5573688745498657}, "ruth": {"emoji": "mrs-claus", "score": 0.5552148818969727}, "beast": {"emoji": "alien-monster", "score": 0.5551457405090332}, "somebody": {"emoji": "person-gesturing-ok", "score": 0.5548757314682007}, "nobody": {"emoji": "person-gesturing-no", "score": 0.5539982318878174}, "tara": {"emoji": "mrs-claus", "score": 0.5531174540519714}, "wasabi": {"emoji": "sushi", "score": 0.5514262318611145}, "done": {"emoji": "hourglass-not-done", "score": 0.5503406524658203}, "age": {"emoji": "older-person", "score": 0.549517035484314}, "photo": {"emoji": "framed-picture", "score": 0.5494637489318848}, "grow": {"emoji": "blossom", "score": 0.5490480065345764}, "single": {"emoji": "repeat-single-button", "score": 0.5480766296386719}, "tha": {"emoji": "leo", "score": 0.5480504035949707}, "rishi": {"emoji": "nazar-amulet", "score": 0.5471937656402588}, "shoot": {"emoji": "shooting-star", "score": 0.5458305478096008}, "hear": {"emoji": "hear-no-evil-monkey", "score": 0.5455366969108582}, "player": {"emoji": "person-playing-handball", "score": 0.5445983409881592}, "champ": {"emoji": "crown", "score": 0.544142484664917}, "screen": {"emoji": "film-projector", "score": 0.5412372350692749}, "audio": {"emoji": "video-camera", "score": 0.5405831336975098}, "big": {"emoji": "grinning-face-with-big-eyes", "score": 0.5393326282501221}, "kyle": {"emoji": "mrs-claus", "score": 0.5386660099029541}, "connection": {"emoji": "link", "score": 0.5380096435546875}, "something": {"emoji": "love-you-gesture", "score": 0.5375421643257141}, "roi": {"emoji": "fleur-de-lis", "score": 0.5364416837692261}, "champion": {"emoji": "crown", "score": 0.5352734923362732}, "vote": {"emoji": "ballot-box-with-ballot", "score": 0.5343482494354248}, "uncle": {"emoji": "boy", "score": 0.5331798791885376}, "half": {"emoji": "first-quarter-moon", "score": 0.5329641103744507}, "see": {"emoji": "watch", "score": 0.5326846837997437}, "taking": {"emoji": "person-taking-bath", "score": 0.5317713618278503}, "level": {"emoji": "level-slider", "score": 0.5310224294662476}, "road": {"emoji": "motorway", "score": 0.5304887890815735}, "wit": {"emoji": "cat-with-wry-smile", "score": 0.5303237438201904}, "ask": {"emoji": "call-me-hand", "score": 0.5296006798744202}, "really": {"emoji": "love-you-gesture", "score": 0.528272807598114}, "thug": {"emoji": "man-supervillain", "score": 0.5273504853248596}, "heartbreak": {"emoji": "face-with-tears-of-joy", "score": 0.5271421074867249}, "russia": {"emoji": "globe-showing-asia-australia", "score": 0.5267437696456909}, "husband": {"emoji": "family", "score": 0.5267333984375}, "tested": {"emoji": "test-tube", "score": 0.524535596370697}, "fly": {"emoji": "flying-saucer", "score": 0.5225327014923096}, "feed": {"emoji": "breast-feeding", "score": 0.5223005414009094}, "dad": {"emoji": "boy", "score": 0.5219990015029907}, "think": {"emoji": "thinking-face", "score": 0.5216301679611206}, "quirky": {"emoji": "zany-face", "score": 0.5212387442588806}, "triple": {"emoji": "double-curly-loop", "score": 0.5204876065254211}, "brother": {"emoji": "boy", "score": 0.5195391774177551}, "pray": {"emoji": "prayer-beads", "score": 0.5189431309700012}, "hoti": {"emoji": "nazar-amulet", "score": 0.5185422897338867}, "build": {"emoji": "building-construction", "score": 0.5182955861091614}, "jungle": {"emoji": "desert-island", "score": 0.5170184373855591}, "throat": {"emoji": "nose", "score": 0.5164586305618286}, "color": {"emoji": "white-flower", "score": 0.5152089595794678}, "doctor": {"emoji": "hospital", "score": 0.5143237113952637}, "jordan": {"emoji": "mrs-claus", "score": 0.5120351314544678}, "sri": {"emoji": "hindu-temple", "score": 0.5117921829223633}, "paint": {"emoji": "crayon", "score": 0.511629581451416}, "speechless": {"emoji": "astonished-face", "score": 0.5106557607650757}, "hair": {"emoji": "woman-getting-haircut", "score": 0.5101801753044128}, "eat": {"emoji": "hamburger", "score": 0.510136604309082}, "koi": {"emoji": "fish", "score": 0.5083854794502258}, "new": {"emoji": "new-button", "score": 0.5082492828369141}, "mila": {"emoji": "nazar-amulet", "score": 0.5072544813156128}, "singh": {"emoji": "hindu-temple", "score": 0.5066049098968506}, "kind": {"emoji": "love-you-gesture", "score": 0.5063771605491638}, "poster": {"emoji": "framed-picture", "score": 0.5040397644042969}, "god": {"emoji": "nazar-amulet", "score": 0.5040032863616943}, "amar": {"emoji": "nazar-amulet", "score": 0.5035925507545471}, "nothing": {"emoji": "person-gesturing-no", "score": 0.5035139322280884}, "remind": {"emoji": "reminder-ribbon", "score": 0.5024234056472778}, "league": {"emoji": "cricket-game", "score": 0.5014297962188721}, "sire": {"emoji": "chestnut", "score": 0.5011825561523438}, "corner": {"emoji": "right-arrow-curving-left", "score": 0.5009735226631165}, "hate": {"emoji": "love-letter", "score": 0.500838041305542}, "legend": {"emoji": "star", "score": 0.500391960144043}, "enjoying": {"emoji": "face-savoring-food", "score": 0.5001325607299805}, "designer": {"emoji": "artist-palette", "score": 0.4994601309299469}, "guess": {"emoji": "ok-hand", "score": 0.4994497001171112}, "sister": {"emoji": "girl", "score": 0.4985508322715759}, "josh": {"emoji": "star-of-david", "score": 0.4985498785972595}, "sportsman": {"emoji": "man-golfing", "score": 0.4976408779621124}, "bos": {"emoji": "mrs-claus", "score": 0.4968346953392029}, "baba": {"emoji": "mrs-claus", "score": 0.49460041522979736}, "kim": {"emoji": "leo", "score": 0.49428772926330566}, "lyrical": {"emoji": "musical-notes", "score": 0.49300384521484375}, "want": {"emoji": "love-you-gesture", "score": 0.49269506335258484}, "answer": {"emoji": "question-mark", "score": 0.4921149015426636}, "way": {"emoji": "milky-way", "score": 0.4915936291217804}, "jay": {"emoji": "t-rex", "score": 0.49041634798049927}, "friend": {"emoji": "family", "score": 0.4891514778137207}, "brazil": {"emoji": "globe-showing-europe-africa", "score": 0.48886531591415405}, "sandy": {"emoji": "desert", "score": 0.4888068735599518}, "stylist": {"emoji": "artist-palette", "score": 0.48766642808914185}, "adorable": {"emoji": "baby-chick", "score": 0.4876498281955719}, "director": {"emoji": "chair", "score": 0.4869970679283142}, "wonderful": {"emoji": "love-you-gesture", "score": 0.48697996139526367}, "election": {"emoji": "ballot-box-with-ballot", "score": 0.48670777678489685}, "par": {"emoji": "hole", "score": 0.486206591129303}, "feeling": {"emoji": "sad-but-relieved-face", "score": 0.48570287227630615}, "got": {"emoji": "man-getting-haircut", "score": 0.4851982593536377}, "tonight": {"emoji": "night-with-stars", "score": 0.4850715398788452}, "get": {"emoji": "person-getting-massage", "score": 0.4849492013454437}, "run": {"emoji": "person-running", "score": 0.48487329483032227}, "anniversary": {"emoji": "birthday-cake", "score": 0.4844783544540405}, "increase": {"emoji": "chart-increasing", "score": 0.4828912615776062}, "refrain": {"emoji": "prohibited", "score": 0.48203402757644653}, "dinner": {"emoji": "birthday-cake", "score": 0.48102453351020813}, "teaching": {"emoji": "school", "score": 0.4808855652809143}, "coz": {"emoji": "mrs-claus", "score": 0.4802772104740143}, "gold": {"emoji": "large-blue-diamond", "score": 0.47986844182014465}, "pitch": {"emoji": "soccer-ball", "score": 0.47966453433036804}, "ist": {"emoji": "om", "score": 0.47913891077041626}, "sir": {"emoji": "man-gesturing-ok", "score": 0.47884273529052734}, "yes": {"emoji": "ok-hand", "score": 0.47840017080307007}, "trailer": {"emoji": "tractor", "score": 0.47828033566474915}, "hind": {"emoji": "pig-nose", "score": 0.47793257236480713}, "read": {"emoji": "writing-hand", "score": 0.4775121808052063}, "thing": {"emoji": "love-you-gesture", "score": 0.47639000415802}, "dong": {"emoji": "yen-banknote", "score": 0.4756709933280945}, "happiness": {"emoji": "cat-with-tears-of-joy", "score": 0.4752200245857239}, "morning": {"emoji": "bridge-at-night", "score": 0.4751739799976349}, "whatever": {"emoji": "see-no-evil-monkey", "score": 0.474820077419281}, "mind": {"emoji": "smiling-face-with-heart-eyes", "score": 0.47463053464889526}, "hell": {"emoji": "see-no-evil-monkey", "score": 0.4740890860557556}, "insane": {"emoji": "alien-monster", "score": 0.47390249371528625}, "feel": {"emoji": "love-you-gesture", "score": 0.47305548191070557}, "ride": {"emoji": "horse-racing", "score": 0.47245755791664124}, "award": {"emoji": "trophy", "score": 0.4717627167701721}, "entrepreneur": {"emoji": "man-technologist", "score": 0.47116589546203613}, "brilliance": {"emoji": "sparkle", "score": 0.47065290808677673}, "prevent": {"emoji": "shield", "score": 0.4704912304878235}, "eros": {"emoji": "virgo", "score": 0.4701140522956848}, "spoken": {"emoji": "speaking-head", "score": 0.4700517952442169}, "actually": {"emoji": "see-no-evil-monkey", "score": 0.4685502052307129}, "childhood": {"emoji": "child", "score": 0.46818798780441284}, "earth": {"emoji": "ringed-planet", "score": 0.4681728482246399}, "zee": {"emoji": "leo", "score": 0.46745917201042175}, "part": {"emoji": "part-alternation-mark", "score": 0.4669486880302429}, "rab": {"emoji": "libra", "score": 0.46678048372268677}, "song": {"emoji": "musical-note", "score": 0.4666685163974762}, "backwards": {"emoji": "right-arrow-curving-down", "score": 0.46579164266586304}, "next": {"emoji": "next-track-button", "score": 0.46537235379219055}, "shut": {"emoji": "clamp", "score": 0.4644876718521118}, "truly": {"emoji": "love-you-gesture", "score": 0.46362870931625366}, "know": {"emoji": "see-no-evil-monkey", "score": 0.4622948467731476}, "period": {"emoji": "last-quarter-moon", "score": 0.462055504322052}, "country": {"emoji": "globe-showing-europe-africa", "score": 0.4607774019241333}, "anything": {"emoji": "hourglass-not-done", "score": 0.46005865931510925}, "stree": {"emoji": "mrs-claus", "score": 0.45993366837501526}, "nice": {"emoji": "love-you-gesture", "score": 0.4575057327747345}, "camp": {"emoji": "camping", "score": 0.4566872715950012}, "appreciate": {"emoji": "love-you-gesture", "score": 0.4564889371395111}, "captain": {"emoji": "mate", "score": 0.45602262020111084}, "lovely": {"emoji": "sparkles", "score": 0.45599794387817383}, "listen": {"emoji": "watch", "score": 0.45572125911712646}, "stuck": {"emoji": "locked", "score": 0.4553748369216919}, "warm": {"emoji": "cold-face", "score": 0.4553315341472626}, "feast": {"emoji": "petri-dish", "score": 0.4552464485168457}, "nana": {"emoji": "mrs-claus", "score": 0.45476892590522766}, "overcome": {"emoji": "persevering-face", "score": 0.45365583896636963}, "sadly": {"emoji": "sad-but-relieved-face", "score": 0.45360368490219116}, "carpet": {"emoji": "flat-shoe", "score": 0.45331376791000366}, "message": {"emoji": "love-letter", "score": 0.45251667499542236}, "team": {"emoji": "field-hockey", "score": 0.45230329036712646}, "indoors": {"emoji": "sun-behind-rain-cloud", "score": 0.4517914652824402}, "young": {"emoji": "old-man", "score": 0.451082706451416}, "polite": {"emoji": "cat-with-wry-smile", "score": 0.4506795108318329}, "duality": {"emoji": "yin-yang", "score": 0.4503348767757416}, "sense": {"emoji": "love-you-gesture", "score": 0.45014071464538574}, "winning": {"emoji": "victory-hand", "score": 0.44978833198547363}, "sab": {"emoji": "leo", "score": 0.4494509696960449}, "phew": {"emoji": "mrs-claus", "score": 0.4485955834388733}, "tell": {"emoji": "call-me-hand", "score": 0.44844797253608704}, "tabu": {"emoji": "hindu-temple", "score": 0.4483119249343872}, "bleeding": {"emoji": "face-vomiting", "score": 0.44793617725372314}, "always": {"emoji": "love-you-gesture", "score": 0.44792109727859497}, "boom": {"emoji": "right-anger-bubble", "score": 0.4478369951248169}, "novel": {"emoji": "blue-book", "score": 0.4474905729293823}, "beautiful": {"emoji": "love-hotel", "score": 0.44742730259895325}, "seeing": {"emoji": "face-with-rolling-eyes", "score": 0.4467836618423462}, "onto": {"emoji": "up-down-arrow", "score": 0.44635647535324097}, "city": {"emoji": "metro", "score": 0.4462396502494812}, "bull": {"emoji": "cow", "score": 0.44606083631515503}, "suffer": {"emoji": "worried-face", "score": 0.4459365904331207}, "buddy": {"emoji": "mate", "score": 0.44558531045913696}, "voice": {"emoji": "microphone", "score": 0.44557517766952515}, "hum": {"emoji": "ping-pong", "score": 0.44511789083480835}, "lene": {"emoji": "fleur-de-lis", "score": 0.44418707489967346}, "living": {"emoji": "sleeping-face", "score": 0.4424173831939697}, "say": {"emoji": "worried-face", "score": 0.4422333836555481}, "crazy": {"emoji": "man-gesturing-ok", "score": 0.4421462416648865}, "plan": {"emoji": "package", "score": 0.4412904679775238}, "hour": {"emoji": "eight-oclock", "score": 0.4410199224948883}, "knock": {"emoji": "hammer-and-pick", "score": 0.4395061135292053}, "care": {"emoji": "hospital", "score": 0.4392171800136566}, "exactly": {"emoji": "hourglass-not-done", "score": 0.43836238980293274}, "date": {"emoji": "calendar", "score": 0.4377025365829468}, "going": {"emoji": "thinking-face", "score": 0.43763473629951477}, "cooler": {"emoji": "water-closet", "score": 0.43741950392723083}, "huge": {"emoji": "grinning-face-with-big-eyes", "score": 0.43731120228767395}, "arsenal": {"emoji": "toolbox", "score": 0.4371579885482788}, "wali": {"emoji": "nazar-amulet", "score": 0.4368985891342163}, "start": {"emoji": "stop-sign", "score": 0.43648761510849}, "papa": {"emoji": "mrs-claus", "score": 0.4358464181423187}, "thank": {"emoji": "vulcan-salute", "score": 0.4346294701099396}, "chal": {"emoji": "fleur-de-lis", "score": 0.4339589476585388}, "choice": {"emoji": "pick", "score": 0.4338955283164978}, "crew": {"emoji": "ship", "score": 0.43380609154701233}, "kit": {"emoji": "toolbox", "score": 0.4337886571884155}, "never": {"emoji": "see-no-evil-monkey", "score": 0.43377625942230225}, "fasting": {"emoji": "prayer-beads", "score": 0.4337272346019745}, "wrote": {"emoji": "writing-hand", "score": 0.43364542722702026}, "passion": {"emoji": "love-you-gesture", "score": 0.43270209431648254}, "looking": {"emoji": "thinking-face", "score": 0.4325651526451111}, "truth": {"emoji": "hear-no-evil-monkey", "score": 0.4324072599411011}, "gym": {"emoji": "school", "score": 0.4323200583457947}, "enjoy": {"emoji": "face-savoring-food", "score": 0.43186327815055847}, "album": {"emoji": "guitar", "score": 0.4317426383495331}, "wait": {"emoji": "watch", "score": 0.43174126744270325}, "fun": {"emoji": "love-you-gesture", "score": 0.43168962001800537}, "day": {"emoji": "bridge-at-night", "score": 0.43073830008506775}, "strange": {"emoji": "hear-no-evil-monkey", "score": 0.43058520555496216}, "hone": {"emoji": "nail-polish", "score": 0.4289740324020386}, "brave": {"emoji": "persevering-face", "score": 0.4288080334663391}, "even": {"emoji": "slightly-smiling-face", "score": 0.4286213517189026}, "karo": {"emoji": "diya-lamp", "score": 0.4278077185153961}, "guru": {"emoji": "man-technologist", "score": 0.42727941274642944}, "choose": {"emoji": "pick", "score": 0.42708972096443176}, "biggest": {"emoji": "key", "score": 0.42667537927627563}, "superb": {"emoji": "sparkling-heart", "score": 0.42648428678512573}, "community": {"emoji": "family", "score": 0.426233172416687}, "pleasure": {"emoji": "cat-with-tears-of-joy", "score": 0.42585861682891846}, "mane": {"emoji": "curly-loop", "score": 0.42582666873931885}, "everyone": {"emoji": "call-me-hand", "score": 0.4246899485588074}, "dan": {"emoji": "leo", "score": 0.4246520400047302}, "raj": {"emoji": "hindu-temple", "score": 0.42418724298477173}, "everything": {"emoji": "ok-hand", "score": 0.424068808555603}, "wish": {"emoji": "love-you-gesture", "score": 0.42391884326934814}, "body": {"emoji": "skull", "score": 0.4236258864402771}, "mat": {"emoji": "outbox-tray", "score": 0.42361369729042053}, "every": {"emoji": "one-thirty", "score": 0.42358681559562683}, "sideline": {"emoji": "grimacing-face", "score": 0.4235214591026306}, "take": {"emoji": "person-taking-bath", "score": 0.4232865571975708}, "snob": {"emoji": "nerd-face", "score": 0.4225142002105713}, "gon": {"emoji": "yo-yo", "score": 0.4219282865524292}, "divine": {"emoji": "speak-no-evil-monkey", "score": 0.42172861099243164}, "little": {"emoji": "see-no-evil-monkey", "score": 0.4206770062446594}, "told": {"emoji": "speaking-head", "score": 0.4201928377151489}, "go": {"emoji": "call-me-hand", "score": 0.4193107485771179}, "institution": {"emoji": "bank", "score": 0.41901060938835144}, "live": {"emoji": "watch", "score": 0.4186183214187622}, "beware": {"emoji": "warning", "score": 0.41843152046203613}, "great": {"emoji": "love-you-gesture", "score": 0.4178462624549866}, "assistance": {"emoji": "ear-with-hearing-aid", "score": 0.4178326725959778}, "hard": {"emoji": "fast-forward-button", "score": 0.4178158938884735}, "ani": {"emoji": "ng-button", "score": 0.4171709716320038}, "gill": {"emoji": "carp-streamer", "score": 0.41614049673080444}, "sure": {"emoji": "ok-hand", "score": 0.41561269760131836}, "look": {"emoji": "thinking-face", "score": 0.4153081774711609}, "grab": {"emoji": "hammer-and-pick", "score": 0.414297491312027}, "celebrate": {"emoji": "birthday-cake", "score": 0.41386812925338745}, "pose": {"emoji": "worried-face", "score": 0.41360801458358765}, "author": {"emoji": "books", "score": 0.4135848879814148}, "excited": {"emoji": "disappointed-face", "score": 0.41289907693862915}, "junior": {"emoji": "volleyball", "score": 0.4124569296836853}, "lucky": {"emoji": "sad-but-relieved-face", "score": 0.4120687246322632}, "life": {"emoji": "family", "score": 0.41159164905548096}, "break": {"emoji": "broken-heart", "score": 0.4108240306377411}, "calling": {"emoji": "call-me-hand", "score": 0.4108014404773712}, "talk": {"emoji": "thinking-face", "score": 0.4106150269508362}, "roar": {"emoji": "face-screaming-in-fear", "score": 0.41050779819488525}, "drove": {"emoji": "oncoming-police-car", "score": 0.4099656939506531}, "tune": {"emoji": "wind-chime", "score": 0.40976178646087646}, "concern": {"emoji": "worried-face", "score": 0.4095980226993561}, "sung": {"emoji": "saxophone", "score": 0.4095836877822876}, "stuff": {"emoji": "love-you-gesture", "score": 0.40947940945625305}, "awesome": {"emoji": "love-you-gesture", "score": 0.4093405604362488}, "attack": {"emoji": "bomb", "score": 0.4084326922893524}, "resist": {"emoji": "stop-sign", "score": 0.4083241820335388}, "ready": {"emoji": "anxious-face-with-sweat", "score": 0.4074745774269104}, "please": {"emoji": "call-me-hand", "score": 0.40621671080589294}, "let": {"emoji": "japanese-not-free-of-charge-button", "score": 0.4058796763420105}, "article": {"emoji": "memo", "score": 0.40540239214897156}, "put": {"emoji": "raised-back-of-hand", "score": 0.4051385521888733}, "bless": {"emoji": "love-you-gesture", "score": 0.40499117970466614}, "many": {"emoji": "two-thirty", "score": 0.4049625098705292}, "sit": {"emoji": "watch", "score": 0.40486595034599304}, "keep": {"emoji": "stop-sign", "score": 0.4044271409511566}, "remember": {"emoji": "love-you-gesture", "score": 0.40433230996131897}, "much": {"emoji": "hourglass-not-done", "score": 0.404327929019928}, "hurt": {"emoji": "worried-face", "score": 0.4039801061153412}, "dop": {"emoji": "oden", "score": 0.40392014384269714}, "outdoor": {"emoji": "camping", "score": 0.4038160443305969}, "naik": {"emoji": "scorpio", "score": 0.40338122844696045}, "passing": {"emoji": "japanese-passing-grade-button", "score": 0.4018027186393738}, "happen": {"emoji": "hourglass-not-done", "score": 0.4009510576725006}, "streaming": {"emoji": "video-game", "score": 0.4008280634880066}, "language": {"emoji": "tongue", "score": 0.40057629346847534}, "equation": {"emoji": "puzzle-piece", "score": 0.3996957838535309}, "dare": {"emoji": "love-you-gesture", "score": 0.3992966115474701}, "surely": {"emoji": "love-you-gesture", "score": 0.39919793605804443}, "tragic": {"emoji": "sad-but-relieved-face", "score": 0.3991446793079376}, "forget": {"emoji": "love-you-gesture", "score": 0.3991219997406006}, "apart": {"emoji": "dashing-away", "score": 0.3972141444683075}, "bill": {"emoji": "package", "score": 0.39707714319229126}, "personnel": {"emoji": "rescue-workers-helmet", "score": 0.39660003781318665}, "everlasting": {"emoji": "nazar-amulet", "score": 0.3965234160423279}, "shove": {"emoji": "man-gesturing-ok", "score": 0.39645975828170776}, "taken": {"emoji": "person-taking-bath", "score": 0.396427720785141}, "dignity": {"emoji": "statue-of-liberty", "score": 0.39559274911880493}, "awesomeness": {"emoji": "nerd-face", "score": 0.3955131471157074}, "design": {"emoji": "building-construction", "score": 0.39512398838996887}, "genius": {"emoji": "joker", "score": 0.39481744170188904}, "memory": {"emoji": "brain", "score": 0.39464759826660156}, "doubt": {"emoji": "question-mark", "score": 0.39444786310195923}, "absolutely": {"emoji": "see-no-evil-monkey", "score": 0.3941846489906311}, "winner": {"emoji": "trophy", "score": 0.394182413816452}, "khan": {"emoji": "hindu-temple", "score": 0.3941391706466675}, "welcome": {"emoji": "sad-but-relieved-face", "score": 0.3939051032066345}, "terror": {"emoji": "bomb", "score": 0.39379969239234924}, "ticking": {"emoji": "timer-clock", "score": 0.39372485876083374}, "village": {"emoji": "woman-farmer", "score": 0.39358246326446533}, "keeping": {"emoji": "locked-with-key", "score": 0.3934829533100128}, "lot": {"emoji": "couple-with-heart", "score": 0.3934418261051178}, "turn": {"emoji": "stop-sign", "score": 0.393159955739975}, "theta": {"emoji": "input-latin-uppercase", "score": 0.3926703929901123}, "push": {"emoji": "ram", "score": 0.39264440536499023}, "squad": {"emoji": "man-playing-handball", "score": 0.39217764139175415}, "hope": {"emoji": "sad-but-relieved-face", "score": 0.3921028971672058}, "faith": {"emoji": "church", "score": 0.3920666575431824}, "preorder": {"emoji": "japanese-discount-button", "score": 0.3916104733943939}, "year": {"emoji": "nine-thirty", "score": 0.3911300301551819}, "avoid": {"emoji": "stop-sign", "score": 0.3910464346408844}, "delighted": {"emoji": "disappointed-face", "score": 0.39098674058914185}, "side": {"emoji": "right-arrow-curving-down", "score": 0.390677809715271}, "understand": {"emoji": "confused-face", "score": 0.3906747102737427}, "freak": {"emoji": "man-cartwheeling", "score": 0.39057525992393494}, "qualifier": {"emoji": "man-playing-handball", "score": 0.3904123306274414}, "strength": {"emoji": "flexed-biceps", "score": 0.38926103711128235}, "expect": {"emoji": "disappointed-face", "score": 0.3887638747692108}, "silence": {"emoji": "hushed-face", "score": 0.38859325647354126}, "tera": {"emoji": "libra", "score": 0.38752713799476624}, "forever": {"emoji": "smiling-face-with-hearts", "score": 0.3875136375427246}, "beauty": {"emoji": "sparkle", "score": 0.3864222764968872}, "midst": {"emoji": "weary-face", "score": 0.3864157199859619}, "balboa": {"emoji": "leo", "score": 0.3860693573951721}, "disappoint": {"emoji": "disappointed-face", "score": 0.3853752017021179}, "goa": {"emoji": "om", "score": 0.385353684425354}, "case": {"emoji": "woman-judge", "score": 0.3842182159423828}, "aho": {"emoji": "libra", "score": 0.3841692805290222}, "come": {"emoji": "hear-no-evil-monkey", "score": 0.3834648132324219}, "cheer": {"emoji": "face-with-tears-of-joy", "score": 0.38267242908477783}, "consider": {"emoji": "thinking-face", "score": 0.38231995701789856}, "coming": {"emoji": "face-with-rolling-eyes", "score": 0.3822742700576782}, "entertaining": {"emoji": "zany-face", "score": 0.3820713758468628}, "ended": {"emoji": "last-quarter-moon", "score": 0.3818274140357971}, "lazy": {"emoji": "sloth", "score": 0.380537748336792}, "lead": {"emoji": "victory-hand", "score": 0.3803427815437317}, "rounder": {"emoji": "pick", "score": 0.3794482946395874}, "intimate": {"emoji": "person-in-steamy-room", "score": 0.3792358636856079}, "unbelievable": {"emoji": "sad-but-relieved-face", "score": 0.3791531026363373}, "find": {"emoji": "check-box-with-check", "score": 0.37845051288604736}, "pushing": {"emoji": "rolling-on-the-floor-laughing", "score": 0.3780425190925598}, "coop": {"emoji": "house", "score": 0.3779221177101135}, "final": {"emoji": "first-quarter-moon", "score": 0.3775786757469177}, "wow": {"emoji": "love-you-gesture", "score": 0.37744367122650146}, "luck": {"emoji": "fortune-cookie", "score": 0.37740612030029297}, "youth": {"emoji": "man-student", "score": 0.3771285116672516}, "season": {"emoji": "night-with-stars", "score": 0.3771248459815979}, "congratulatory": {"emoji": "japanese-congratulations-button", "score": 0.37711602449417114}, "miss": {"emoji": "disappointed-face", "score": 0.3768450617790222}, "seeking": {"emoji": "pleading-face", "score": 0.3764260411262512}, "amazing": {"emoji": "love-you-gesture", "score": 0.3756003975868225}, "path": {"emoji": "right-arrow-curving-down", "score": 0.37549060583114624}, "awkward": {"emoji": "pensive-face", "score": 0.3748862147331238}, "happiest": {"emoji": "cat-with-tears-of-joy", "score": 0.37448322772979736}, "attract": {"emoji": "magnet", "score": 0.3740762770175934}, "telling": {"emoji": "thinking-face", "score": 0.37407422065734863}, "petition": {"emoji": "love-letter", "score": 0.3739652633666992}, "power": {"emoji": "high-voltage", "score": 0.3738225996494293}, "good": {"emoji": "ok-hand", "score": 0.37371325492858887}, "amen": {"emoji": "prayer-beads", "score": 0.3735160529613495}, "word": {"emoji": "speak-no-evil-monkey", "score": 0.3733302354812622}, "doc": {"emoji": "movie-camera", "score": 0.3732355237007141}, "time": {"emoji": "one-thirty", "score": 0.3730913996696472}, "fight": {"emoji": "game-die", "score": 0.37249526381492615}, "work": {"emoji": "construction-worker", "score": 0.3724833130836487}, "tomorrow": {"emoji": "bridge-at-night", "score": 0.3722414970397949}, "tone": {"emoji": "muted-speaker", "score": 0.37182044982910156}, "minister": {"emoji": "file-cabinet", "score": 0.371576726436615}, "blank": {"emoji": "hollow-red-circle", "score": 0.3703978359699249}, "buzzing": {"emoji": "drooling-face", "score": 0.3703466057777405}, "zero": {"emoji": "minus-sign", "score": 0.3702394366264343}, "grosser": {"emoji": "cinema", "score": 0.36934125423431396}, "dev": {"emoji": "mage", "score": 0.3692357540130615}, "born": {"emoji": "baby", "score": 0.36897313594818115}, "join": {"emoji": "stop-sign", "score": 0.36838358640670776}, "rocky": {"emoji": "foggy", "score": 0.3680606186389923}, "went": {"emoji": "dove", "score": 0.3679652810096741}, "feather": {"emoji": "peacock", "score": 0.36698201298713684}, "finally": {"emoji": "sad-but-relieved-face", "score": 0.3667352497577667}, "line": {"emoji": "cross-mark-button", "score": 0.3667091429233551}, "aka": {"emoji": "taurus", "score": 0.36668622493743896}, "succession": {"emoji": "straight-ruler", "score": 0.3663420081138611}, "said": {"emoji": "speaking-head", "score": 0.3660210072994232}, "hain": {"emoji": "om", "score": 0.3657307028770447}, "news": {"emoji": "newspaper", "score": 0.3653758466243744}, "saw": {"emoji": "grinning-face-with-big-eyes", "score": 0.36368560791015625}, "believe": {"emoji": "worried-face", "score": 0.36366888880729675}, "need": {"emoji": "anxious-face-with-sweat", "score": 0.36351096630096436}, "remove": {"emoji": "shield", "score": 0.36343151330947876}, "moving": {"emoji": "rolling-on-the-floor-laughing", "score": 0.36314719915390015}, "job": {"emoji": "man-office-worker", "score": 0.3630203306674957}, "raider": {"emoji": "chestnut", "score": 0.3629908859729767}, "learning": {"emoji": "school", "score": 0.3629518449306488}, "trapped": {"emoji": "rescue-workers-helmet", "score": 0.3626907169818878}, "account": {"emoji": "bank", "score": 0.3625916838645935}, "dear": {"emoji": "two-hearts", "score": 0.36245298385620117}, "junk": {"emoji": "pile-of-poo", "score": 0.36233603954315186}, "performance": {"emoji": "musical-score", "score": 0.3618420362472534}, "parody": {"emoji": "zany-face", "score": 0.36183980107307434}, "catch": {"emoji": "watch", "score": 0.3616425693035126}, "fan": {"emoji": "star", "score": 0.361571729183197}, "fused": {"emoji": "alembic", "score": 0.3613053858280182}, "air": {"emoji": "radio", "score": 0.360622376203537}, "agree": {"emoji": "disappointed-face", "score": 0.36059218645095825}, "acting": {"emoji": "speaking-head", "score": 0.36043113470077515}, "guessing": {"emoji": "rolling-on-the-floor-laughing", "score": 0.36010992527008057}, "story": {"emoji": "puzzle-piece", "score": 0.35927945375442505}, "surprise": {"emoji": "disappointed-face", "score": 0.35920238494873047}, "exercise": {"emoji": "person-lifting-weights", "score": 0.35870420932769775}, "doubtful": {"emoji": "worried-face", "score": 0.3581763207912445}, "proclaiming": {"emoji": "reminder-ribbon", "score": 0.3577928841114044}, "thriller": {"emoji": "film-frames", "score": 0.357113778591156}, "blessed": {"emoji": "love-you-gesture", "score": 0.357107937335968}, "happening": {"emoji": "hourglass-not-done", "score": 0.35657885670661926}, "mine": {"emoji": "mountain-railway", "score": 0.35639697313308716}, "deserve": {"emoji": "disappointed-face", "score": 0.3558999300003052}, "rest": {"emoji": "rolling-on-the-floor-laughing", "score": 0.3558095097541809}, "tweet": {"emoji": "love-letter", "score": 0.3555337190628052}, "august": {"emoji": "mrs-claus", "score": 0.35530558228492737}, "desire": {"emoji": "love-you-gesture", "score": 0.35483506321907043}, "premium": {"emoji": "speaker-low-volume", "score": 0.354552686214447}, "give": {"emoji": "hammer-and-pick", "score": 0.3540576696395874}, "waiting": {"emoji": "watch", "score": 0.35335320234298706}, "send": {"emoji": "plus-sign", "score": 0.3533211946487427}, "taught": {"emoji": "man-teacher", "score": 0.3532758057117462}, "ditto": {"emoji": "ok-hand", "score": 0.3529402017593384}, "edge": {"emoji": "victory-hand", "score": 0.352780282497406}, "inflation": {"emoji": "currency-exchange", "score": 0.35266634821891785}, "breathe": {"emoji": "nauseated-face", "score": 0.35252130031585693}, "touched": {"emoji": "crossed-fingers", "score": 0.35250744223594666}, "united": {"emoji": "peace-symbol", "score": 0.35206103324890137}, "forgetting": {"emoji": "thinking-face", "score": 0.35202550888061523}, "jam": {"emoji": "guitar", "score": 0.3520190119743347}, "stream": {"emoji": "water-wave", "score": 0.35186129808425903}, "perspective": {"emoji": "thinking-face", "score": 0.35150185227394104}, "gang": {"emoji": "man-detective", "score": 0.34984368085861206}, "deserved": {"emoji": "sad-but-relieved-face", "score": 0.3496476411819458}, "golden": {"emoji": "sparkle", "score": 0.3494946360588074}, "hopefully": {"emoji": "ok-hand", "score": 0.34928399324417114}, "took": {"emoji": "person-taking-bath", "score": 0.34884464740753174}, "advice": {"emoji": "warning", "score": 0.34832680225372314}, "taut": {"emoji": "pensive-face", "score": 0.34790414571762085}, "making": {"emoji": "rolling-on-the-floor-laughing", "score": 0.3476496934890747}, "try": {"emoji": "love-you-gesture", "score": 0.34762921929359436}, "unending": {"emoji": "weary-face", "score": 0.34743261337280273}, "bump": {"emoji": "tear-off-calendar", "score": 0.3474246561527252}, "evidently": {"emoji": "speak-no-evil-monkey", "score": 0.3472180664539337}, "matter": {"emoji": "question-mark", "score": 0.3467177152633667}, "lump": {"emoji": "brown-heart", "score": 0.3461425006389618}, "reason": {"emoji": "sake", "score": 0.3458970785140991}, "clarification": {"emoji": "input-latin-letters", "score": 0.34569352865219116}, "lesson": {"emoji": "reminder-ribbon", "score": 0.34564799070358276}, "apparently": {"emoji": "man-gesturing-no", "score": 0.34547585248947144}, "step": {"emoji": "stop-sign", "score": 0.3447319269180298}, "pay": {"emoji": "plus-sign", "score": 0.3439352512359619}, "dream": {"emoji": "cat-with-tears-of-joy", "score": 0.34365901350975037}, "dada": {"emoji": "scorpio", "score": 0.3435242772102356}, "pavan": {"emoji": "om", "score": 0.3432499170303345}, "condemn": {"emoji": "stop-sign", "score": 0.3430910110473633}, "raw": {"emoji": "roasted-sweet-potato", "score": 0.34309035539627075}, "given": {"emoji": "no-one-under-eighteen", "score": 0.34301555156707764}, "make": {"emoji": "check-mark", "score": 0.3425455689430237}, "nominate": {"emoji": "pick", "score": 0.3420494794845581}, "directed": {"emoji": "direct-hit", "score": 0.3420298397541046}, "immense": {"emoji": "growing-heart", "score": 0.34151747822761536}, "manager": {"emoji": "speaking-head", "score": 0.34138810634613037}, "came": {"emoji": "rose", "score": 0.3411664068698883}, "towards": {"emoji": "downwards-button", "score": 0.34105002880096436}, "twitter": {"emoji": "spider-web", "score": 0.3405429720878601}, "fantastic": {"emoji": "love-you-gesture", "score": 0.34014391899108887}, "calm": {"emoji": "hushed-face", "score": 0.3400754928588867}, "hence": {"emoji": "sake", "score": 0.33946138620376587}, "minor": {"emoji": "mechanical-leg", "score": 0.3391886353492737}, "best": {"emoji": "top-hat", "score": 0.33825403451919556}, "set": {"emoji": "locked-with-key", "score": 0.33767515420913696}, "confusion": {"emoji": "right-anger-bubble", "score": 0.337126225233078}, "turf": {"emoji": "field-hockey", "score": 0.3370937407016754}, "chaos": {"emoji": "right-anger-bubble", "score": 0.33640578389167786}, "courtesy": {"emoji": "check-box-with-check", "score": 0.3361857533454895}, "used": {"emoji": "linked-paperclips", "score": 0.3358927369117737}, "beginning": {"emoji": "part-alternation-mark", "score": 0.33556586503982544}, "fought": {"emoji": "victory-hand", "score": 0.3352293372154236}, "finance": {"emoji": "bank", "score": 0.33500584959983826}, "till": {"emoji": "twelve-oclock", "score": 0.33454596996307373}, "affected": {"emoji": "direct-hit", "score": 0.33442217111587524}, "explain": {"emoji": "speak-no-evil-monkey", "score": 0.334145188331604}, "ala": {"emoji": "star-of-david", "score": 0.3337908387184143}, "gathering": {"emoji": "moon-viewing-ceremony", "score": 0.3333035707473755}, "history": {"emoji": "books", "score": 0.3332403898239136}, "retirement": {"emoji": "graduation-cap", "score": 0.3328392505645752}, "inspiring": {"emoji": "love-you-gesture", "score": 0.33123552799224854}, "must": {"emoji": "no-one-under-eighteen", "score": 0.33116400241851807}, "analyst": {"emoji": "man-scientist", "score": 0.3310958743095398}, "trouble": {"emoji": "red-triangle-pointed-up", "score": 0.3308422267436981}, "bye": {"emoji": "victory-hand", "score": 0.33035290241241455}, "change": {"emoji": "airplane-departure", "score": 0.33009058237075806}, "learn": {"emoji": "information", "score": 0.32993432879447937}, "defense": {"emoji": "man-guard", "score": 0.32915353775024414}, "would": {"emoji": "hourglass-not-done", "score": 0.3283883333206177}, "slip": {"emoji": "roll-of-paper", "score": 0.32784295082092285}, "begin": {"emoji": "stop-sign", "score": 0.3265971541404724}, "tour": {"emoji": "bus-stop", "score": 0.3265409767627716}, "powered": {"emoji": "electric-plug", "score": 0.32618218660354614}, "cue": {"emoji": "studio-microphone", "score": 0.3259068727493286}, "respect": {"emoji": "love-you-gesture", "score": 0.3248528242111206}, "priority": {"emoji": "key", "score": 0.3244677186012268}, "considered": {"emoji": "prohibited", "score": 0.3240218758583069}, "merry": {"emoji": "zany-face", "score": 0.3231811225414276}, "importance": {"emoji": "key", "score": 0.32315143942832947}, "stall": {"emoji": "shopping-cart", "score": 0.32302770018577576}, "contender": {"emoji": "star", "score": 0.32238370180130005}, "encouragement": {"emoji": "love-you-gesture", "score": 0.32199689745903015}, "stage": {"emoji": "musical-score", "score": 0.3219285309314728}, "convince": {"emoji": "pleading-face", "score": 0.32178449630737305}, "cast": {"emoji": "night-with-stars", "score": 0.32169124484062195}, "collected": {"emoji": "registered", "score": 0.3215979337692261}, "prepared": {"emoji": "face-savoring-food", "score": 0.3215484023094177}, "follow": {"emoji": "stop-sign", "score": 0.32142388820648193}, "wealth": {"emoji": "fortune-cookie", "score": 0.32132261991500854}, "meant": {"emoji": "sake", "score": 0.3211958408355713}, "drawn": {"emoji": "locked-with-pen", "score": 0.32082599401474}, "premiere": {"emoji": "film-projector", "score": 0.3207286298274994}, "counting": {"emoji": "ballot-box-with-ballot", "score": 0.32063573598861694}, "independence": {"emoji": "peace-symbol", "score": 0.32059526443481445}, "unit": {"emoji": "division-sign", "score": 0.3202274739742279}, "tried": {"emoji": "dove", "score": 0.32014912366867065}, "drag": {"emoji": "tear-off-calendar", "score": 0.31968221068382263}, "display": {"emoji": "moon-viewing-ceremony", "score": 0.319619745016098}, "remain": {"emoji": "locked-with-key", "score": 0.3193702697753906}, "giving": {"emoji": "people-holding-hands", "score": 0.31934693455696106}, "chat": {"emoji": "japanese-congratulations-button", "score": 0.3190554976463318}, "debut": {"emoji": "star", "score": 0.3189938962459564}, "wake": {"emoji": "nauseated-face", "score": 0.3188614547252655}, "inspiration": {"emoji": "artist-palette", "score": 0.3188069462776184}, "donate": {"emoji": "drop-of-blood", "score": 0.31879550218582153}, "annual": {"emoji": "calendar", "score": 0.3184468150138855}, "visit": {"emoji": "call-me-hand", "score": 0.318245530128479}, "version": {"emoji": "package", "score": 0.3179076313972473}, "classified": {"emoji": "prohibited", "score": 0.3177564740180969}, "interact": {"emoji": "watch", "score": 0.31658926606178284}, "contribute": {"emoji": "plus-sign", "score": 0.31639066338539124}, "supporter": {"emoji": "man-technologist", "score": 0.3161381781101227}, "ever": {"emoji": "question-mark", "score": 0.3159095346927643}, "show": {"emoji": "television", "score": 0.31576576828956604}, "raid": {"emoji": "bomb", "score": 0.31548717617988586}, "backing": {"emoji": "thumbs-up", "score": 0.3153184652328491}, "advance": {"emoji": "admission-tickets", "score": 0.313839852809906}, "insanity": {"emoji": "right-anger-bubble", "score": 0.31354689598083496}, "industry": {"emoji": "automobile", "score": 0.3128843605518341}, "spend": {"emoji": "partying-face", "score": 0.3128345012664795}, "slim": {"emoji": "speaker-low-volume", "score": 0.3127653896808624}, "carry": {"emoji": "check-box-with-check", "score": 0.31274521350860596}, "conversation": {"emoji": "call-me-hand", "score": 0.31255659461021423}, "repay": {"emoji": "money-with-wings", "score": 0.3121820092201233}, "filled": {"emoji": "flushed-face", "score": 0.31202420592308044}, "chance": {"emoji": "2nd-place-medal", "score": 0.3117569088935852}, "stay": {"emoji": "locked", "score": 0.31152069568634033}, "prime": {"emoji": "key", "score": 0.3111861050128937}, "trying": {"emoji": "thinking-face", "score": 0.3106451630592346}, "meeting": {"emoji": "ear-with-hearing-aid", "score": 0.30991750955581665}, "cakewalk": {"emoji": "hourglass-not-done", "score": 0.3092153072357178}, "mission": {"emoji": "man-astronaut", "score": 0.3091810941696167}, "professional": {"emoji": "field-hockey", "score": 0.3085637092590332}, "bring": {"emoji": "face-with-rolling-eyes", "score": 0.30838742852211}, "group": {"emoji": "umbrella", "score": 0.30831393599510193}, "effort": {"emoji": "goal-net", "score": 0.30824559926986694}, "observation": {"emoji": "hospital", "score": 0.30804067850112915}, "promotion": {"emoji": "division-sign", "score": 0.3064427375793457}, "commitment": {"emoji": "love-letter", "score": 0.3061438798904419}, "maximum": {"emoji": "high-voltage", "score": 0.3053598701953888}, "becoming": {"emoji": "growing-heart", "score": 0.3052408993244171}, "support": {"emoji": "input-numbers", "score": 0.30519434809684753}, "launch": {"emoji": "new-moon", "score": 0.30501288175582886}, "phase": {"emoji": "building-construction", "score": 0.30461448431015015}, "helping": {"emoji": "raising-hands", "score": 0.30424821376800537}, "working": {"emoji": "speaking-head", "score": 0.30328208208084106}, "well": {"emoji": "high-heeled-shoe", "score": 0.3028370440006256}, "buy": {"emoji": "stop-sign", "score": 0.30269598960876465}, "represent": {"emoji": "disappointed-face", "score": 0.3026452958583832}, "teaser": {"emoji": "video-game", "score": 0.3026447296142578}, "seen": {"emoji": "face-screaming-in-fear", "score": 0.302513986825943}, "discerning": {"emoji": "high-heeled-shoe", "score": 0.30202624201774597}, "err": {"emoji": "ok-hand", "score": 0.30188503861427307}, "movement": {"emoji": "leaf-fluttering-in-wind", "score": 0.3018009066581726}, "embarrass": {"emoji": "shield", "score": 0.3016045093536377}, "focus": {"emoji": "eye", "score": 0.3010578155517578}, "situation": {"emoji": "sad-but-relieved-face", "score": 0.30054113268852234}, "elaborate": {"emoji": "heart-decoration", "score": 0.2997382879257202}, "yesterday": {"emoji": "bridge-at-night", "score": 0.29881665110588074}, "wishing": {"emoji": "call-me-hand", "score": 0.2985358238220215}, "return": {"emoji": "airplane-departure", "score": 0.2981990575790405}, "missing": {"emoji": "left-luggage", "score": 0.29736799001693726}, "economics": {"emoji": "left-speech-bubble", "score": 0.29728883504867554}, "promise": {"emoji": "love-you-gesture", "score": 0.29726070165634155}, "momentum": {"emoji": "victory-hand", "score": 0.2962936460971832}, "help": {"emoji": "ear-with-hearing-aid", "score": 0.295705109834671}, "consumption": {"emoji": "tropical-drink", "score": 0.29486826062202454}, "workshop": {"emoji": "toolbox", "score": 0.29479309916496277}, "study": {"emoji": "woman-scientist", "score": 0.29432281851768494}, "career": {"emoji": "graduation-cap", "score": 0.29405659437179565}, "typical": {"emoji": "old-key", "score": 0.2940326929092407}, "leadership": {"emoji": "person-in-lotus-position", "score": 0.29372286796569824}, "cause": {"emoji": "face-screaming-in-fear", "score": 0.29367244243621826}, "model": {"emoji": "bust-in-silhouette", "score": 0.293587863445282}, "today": {"emoji": "bridge-at-night", "score": 0.2932584285736084}, "usual": {"emoji": "slightly-frowning-face", "score": 0.29305800795555115}, "future": {"emoji": "new-moon-face", "score": 0.29250216484069824}, "legacy": {"emoji": "baggage-claim", "score": 0.29175814986228943}, "save": {"emoji": "bell-with-slash", "score": 0.291465163230896}, "decision": {"emoji": "airplane-departure", "score": 0.29102644324302673}, "journey": {"emoji": "train", "score": 0.29021310806274414}, "success": {"emoji": "victory-hand", "score": 0.29012033343315125}, "beta": {"emoji": "japanese-application-button", "score": 0.28951331973075867}, "tradition": {"emoji": "trident-emblem", "score": 0.2882792353630066}, "move": {"emoji": "stop-sign", "score": 0.28776752948760986}, "experience": {"emoji": "input-numbers", "score": 0.287258118391037}, "session": {"emoji": "speaker-high-volume", "score": 0.2861059904098511}, "swash": {"emoji": "sparkles", "score": 0.2857823371887207}, "suggest": {"emoji": "confounded-face", "score": 0.2852226793766022}, "posting": {"emoji": "page-facing-up", "score": 0.28275126218795776}, "spread": {"emoji": "rolling-on-the-floor-laughing", "score": 0.282027006149292}, "topical": {"emoji": "adhesive-bandage", "score": 0.28131765127182007}, "may": {"emoji": "see-no-evil-monkey", "score": 0.2813125550746918}, "habit": {"emoji": "four-leaf-clover", "score": 0.28088945150375366}, "thanks": {"emoji": "vulcan-salute", "score": 0.28021812438964844}, "competition": {"emoji": "sports-medal", "score": 0.28020936250686646}, "worked": {"emoji": "speaking-head", "score": 0.2795008420944214}, "tagged": {"emoji": "red-triangle-pointed-up", "score": 0.2779167890548706}, "excellence": {"emoji": "performing-arts", "score": 0.2778598666191101}, "distributed": {"emoji": "linked-paperclips", "score": 0.2777692377567291}, "supporting": {"emoji": "raising-hands", "score": 0.2761847972869873}, "campaign": {"emoji": "man-raising-hand", "score": 0.27617794275283813}, "shah": {"emoji": "diya-lamp", "score": 0.2751319110393524}, "tiff": {"emoji": "kissing-cat", "score": 0.274852454662323}, "made": {"emoji": "no-one-under-eighteen", "score": 0.273573100566864}, "intent": {"emoji": "prohibited", "score": 0.2732178270816803}, "manner": {"emoji": "milky-way", "score": 0.2726626992225647}, "association": {"emoji": "club-suit", "score": 0.2724035978317261}, "fact": {"emoji": "no-one-under-eighteen", "score": 0.2720658779144287}, "count": {"emoji": "slightly-smiling-face", "score": 0.2715369462966919}, "action": {"emoji": "club-suit", "score": 0.2714659869670868}, "become": {"emoji": "blossom", "score": 0.27122917771339417}, "lifetime": {"emoji": "older-person", "score": 0.2701408267021179}, "sentinel": {"emoji": "cityscape-at-dusk", "score": 0.26937031745910645}, "decided": {"emoji": "raised-back-of-hand", "score": 0.267213374376297}, "chose": {"emoji": "pick", "score": 0.26562008261680603}, "continue": {"emoji": "stop-sign", "score": 0.2632838189601898}, "opportunity": {"emoji": "love-you-gesture", "score": 0.2610369920730591}, "addition": {"emoji": "plus-sign", "score": 0.25822198390960693}, "premier": {"emoji": "top-hat", "score": 0.2565605938434601}, "discretion": {"emoji": "prohibited", "score": 0.2556599974632263}, "release": {"emoji": "label", "score": 0.25561416149139404}, "order": {"emoji": "check-box-with-check", "score": 0.2552022337913513}, "awareness": {"emoji": "raising-hands", "score": 0.2527838945388794}, "announce": {"emoji": "disappointed-face", "score": 0.25160953402519226}, "produced": {"emoji": "alembic", "score": 0.2476768046617508}, "possible": {"emoji": "neutral-face", "score": 0.24738436937332153}, "bond": {"emoji": "dollar-banknote", "score": 0.246999591588974}, "spent": {"emoji": "raised-back-of-hand", "score": 0.24127739667892456}, "belated": {"emoji": "question-mark", "score": 0.24122460186481476}, "devoted": {"emoji": "closed-book", "score": 0.2382010668516159}, "efficacy": {"emoji": "safety-vest", "score": 0.2372257560491562}, "outstanding": {"emoji": "receipt", "score": 0.23507891595363617}, "becomes": {"emoji": "see-no-evil-monkey", "score": 0.2345537543296814}, "auction": {"emoji": "moon-viewing-ceremony", "score": 0.2331550121307373}, "venture": {"emoji": "blossom", "score": 0.20517216622829437}}, "interests": {"thank": 384, "birthday": 113, "ruth": 82, "love": 63, "day": 46, "luck": 38, "brother": 36, "year": 36, "done": 33, "happy": 32, "gayatri": 30, "well": 30, "team": 27, "see": 26, "friend": 25, "bunty": 24, "good": 23, "let": 23, "earth": 23, "today": 22, "come": 21, "yes": 21, "support": 21, "believe": 19, "time": 18, "work": 18, "lot": 17, "win": 16, "watch": 16, "looking": 15, "wait": 15, "release": 15, "film": 15, "season": 14, "buddy": 14, "know": 14, "hope": 14, "power": 13, "please": 13, "sir": 13, "keep": 13, "always": 12, "look": 12, "get": 12, "tania": 12, "god": 11, "wishing": 11, "rohan": 10, "best": 10, "try": 10, "think": 10, "man": 10, "full": 9, "winning": 9, "show": 9, "stay": 9, "bless": 9, "big": 9, "mon": 9, "game": 9, "welcome": 9, "sport": 9, "way": 9, "news": 9, "making": 8, "people": 8, "many": 8, "football": 8, "need": 8, "new": 8, "night": 8, "life": 8, "kind": 8, "uncle": 8, "hate": 8, "tonight": 7, "thanks": 7, "raj": 7, "coming": 7, "hard": 7, "made": 7, "respect": 7, "wow": 7, "help": 7, "hey": 7, "angel": 7, "great": 7, "tomorrow": 7, "dream": 7, "listen": 7, "hug": 7, "tweet": 7, "legend": 6, "blessed": 6, "debut": 6, "song": 6, "thing": 6, "world": 6, "watching": 6, "trailer": 6, "question": 6, "one": 6, "trying": 6, "going": 6, "dear": 6, "sentinel": 6, "part": 5, "journey": 5, "breathe": 5, "absolutely": 5, "morning": 5, "match": 5, "family": 5, "wish": 5, "remember": 5, "got": 5, "beautiful": 5, "video": 5, "hear": 5, "continue": 5, "make": 5, "truth": 5, "smiling": 5, "check": 5, "captain": 5, "agree": 5, "vote": 4, "may": 4, "outstanding": 4, "home": 4, "action": 4, "sandy": 4, "anna": 4, "seeing": 4, "sign": 4, "play": 4, "pleasure": 4, "future": 4, "blue": 4, "enjoy": 4, "boy": 4, "sister": 4, "call": 4, "take": 4, "fan": 4, "stop": 4, "buy": 4, "seen": 4, "player": 4, "doctor": 4, "country": 4, "singh": 4, "attack": 4, "something": 4, "would": 4, "feel": 4, "meant": 4, "mind": 4, "start": 4, "amen": 4, "album": 4, "dada": 3, "forget": 3, "want": 3, "cricket": 3, "cool": 3, "director": 3, "give": 3, "live": 3, "stadium": 3, "book": 3, "link": 3, "line": 3, "retirement": 3, "cup": 3, "hour": 3, "right": 3, "anniversary": 3, "anything": 3, "much": 3, "golden": 3, "shooting": 3, "filled": 3, "tara": 3, "face": 3, "chance": 3, "taken": 3, "opportunity": 3, "chin": 3, "becomes": 3, "unit": 3, "becoming": 3, "young": 3, "join": 3, "running": 3, "working": 3, "back": 3, "stage": 3, "advice": 3, "amazing": 3, "queen": 3, "saw": 3, "count": 3, "care": 3, "truly": 3, "baby": 3, "baba": 3, "naik": 3, "champ": 3, "khan": 3, "word": 3, "read": 3, "star": 3, "hain": 3, "track": 3, "experience": 2, "bridge": 2, "living": 2, "cause": 2, "put": 2, "pink": 2, "jam": 2, "studio": 2, "rest": 2, "went": 2, "son": 2, "catch": 2, "papa": 2, "somebody": 2, "leadership": 2, "never": 2, "wake": 2, "taught": 2, "guru": 2, "passion": 2, "actor": 2, "guy": 2, "mate": 2, "zee": 2, "really": 2, "crew": 2, "premiere": 2, "lucky": 2, "final": 2, "half": 2, "giving": 2, "child": 2, "husband": 2, "wife": 2, "election": 2, "run": 2, "must": 2, "learn": 2, "fun": 2, "stuck": 2, "wonderful": 2, "group": 2, "round": 2, "raider": 2, "sri": 2, "shah": 2, "raid": 2, "dad": 2, "advance": 2, "getting": 2, "sorry": 2, "awesome": 2, "post": 2, "supporter": 2, "minister": 2, "thought": 2, "traffic": 2, "mission": 2, "towards": 2, "twitter": 2, "hell": 2, "guessing": 2, "chicken": 2, "club": 2, "beginning": 2, "nep": 2, "matter": 2, "movie": 2, "gang": 2, "cinema": 2, "next": 2, "directed": 2, "picture": 2, "father": 2, "brave": 2, "head": 2, "childhood": 2, "car": 2, "left": 2, "send": 2, "exactly": 2, "appreciate": 2, "reason": 2, "superb": 2, "yesterday": 2, "light": 2, "feeling": 2, "celebrate": 2, "inspiration": 2, "biggest": 2, "ani": 2, "focus": 2, "dinner": 2, "age": 2, "find": 2, "deserved": 2, "talk": 2, "represent": 2, "mat": 2, "industry": 2, "happiness": 2, "nobody": 2, "ride": 2, "begin": 2, "spend": 2, "health": 2, "jungle": 2, "photo": 2, "story": 2, "career": 2, "lady": 2, "genius": 2, "poster": 2, "phew": 2, "bye": 2, "become": 2, "learning": 2, "article": 2, "bring": 2, "insanity": 2, "stall": 2, "dignity": 2, "heart": 2, "message": 2, "junior": 2, "prime": 2, "gill": 2, "first": 2, "say": 2, "hone": 2, "acting": 2, "divine": 2, "collected": 2, "tragic": 2, "happening": 2, "deserve": 2, "till": 2, "choice": 2, "consider": 2, "mine": 2, "hopefully": 2, "knock": 2, "park": 2, "eros": 2, "walk": 2, "belated": 2, "understand": 2, "champion": 2, "sleeping": 2, "considered": 2, "parody": 2, "account": 2, "sauce": 1, "took": 1, "commitment": 1, "backing": 1, "equation": 1, "follow": 1, "display": 1, "brilliance": 1, "record": 1, "perspective": 1, "scoring": 1, "return": 1, "city": 1, "buzzing": 1, "joy": 1, "gym": 1, "apart": 1, "hit": 1, "turf": 1, "fortress": 1, "grab": 1, "bos": 1, "hoti": 1, "bull": 1, "remain": 1, "sportsman": 1, "rise": 1, "hearing": 1, "speechless": 1, "campaign": 1, "camp": 1, "bead": 1, "sweat": 1, "carry": 1, "band": 1, "golf": 1, "midst": 1, "drawn": 1, "lene": 1, "swash": 1, "entrepreneur": 1, "microscope": 1, "discerning": 1, "premium": 1, "race": 1, "backwards": 1, "competition": 1, "taut": 1, "edge": 1, "seat": 1, "thriller": 1, "cast": 1, "cooler": 1, "triangle": 1, "confusion": 1, "television": 1, "apparently": 1, "mila": 1, "tabu": 1, "consumption": 1, "happiest": 1, "girl": 1, "premier": 1, "league": 1, "winner": 1, "couple": 1, "succession": 1, "arm": 1, "err": 1, "calm": 1, "forgetting": 1, "posting": 1, "supporting": 1, "remind": 1, "tested": 1, "prevent": 1, "nominate": 1, "movement": 1, "visit": 1, "minor": 1, "tha": 1, "fact": 1, "exercise": 1, "blood": 1, "clock": 1, "ticking": 1, "contribute": 1, "blank": 1, "path": 1, "doc": 1, "feather": 1, "jay": 1, "bleeding": 1, "increase": 1, "peace": 1, "assistance": 1, "seeking": 1, "clarification": 1, "order": 1, "annual": 1, "national": 1, "youth": 1, "workshop": 1, "interact": 1, "tera": 1, "chal": 1, "goa": 1, "banana": 1, "single": 1, "tired": 1, "beauty": 1, "onto": 1, "history": 1, "color": 1, "addition": 1, "wealth": 1, "strength": 1, "defence": 1, "rounder": 1, "dong": 1, "kim": 1, "auction": 1, "nana": 1, "pick": 1, "pavan": 1, "die": 1, "everything": 1, "choose": 1, "monkey": 1, "suit": 1, "actually": 1, "roi": 1, "grosser": 1, "united": 1, "petition": 1, "finance": 1, "remove": 1, "used": 1, "wit": 1, "courtesy": 1, "amar": 1, "inflation": 1, "ticket": 1, "strange": 1, "snob": 1, "road": 1, "beta": 1, "shoot": 1, "avoid": 1, "diving": 1, "protect": 1, "raw": 1, "moving": 1, "someone": 1, "apartment": 1, "floor": 1, "squad": 1, "moon": 1, "huge": 1, "travelled": 1, "butter": 1, "beware": 1, "enjoying": 1, "even": 1, "feed": 1, "qualifier": 1, "broken": 1, "version": 1, "awesomeness": 1, "tried": 1, "pitch": 1, "habit": 1, "suggest": 1, "everyone": 1, "manner": 1, "job": 1, "prepared": 1, "ended": 1, "slept": 1, "counting": 1, "loop": 1, "bond": 1, "coop": 1, "topical": 1, "teaser": 1, "cakewalk": 1, "chose": 1, "design": 1, "room": 1, "terror": 1, "memory": 1, "lifetime": 1, "personnel": 1, "condemn": 1, "powered": 1, "par": 1, "trapped": 1, "web": 1, "evidently": 1, "nothing": 1, "doubtful": 1, "observation": 1, "pose": 1, "kyle": 1, "open": 1, "chaos": 1, "ready": 1, "born": 1, "finally": 1, "told": 1, "corner": 1, "repay": 1, "set": 1, "given": 1, "faffy": 1, "aho": 1, "mib": 1, "little": 1, "surprise": 1, "drove": 1, "feast": 1, "forever": 1, "ditto": 1, "marzipan": 1, "plan": 1, "encouragement": 1, "village": 1, "side": 1, "dev": 1, "indoors": 1, "warm": 1, "stylist": 1, "designer": 1, "explain": 1, "elaborate": 1, "hurt": 1, "suffer": 1, "lesson": 1, "grow": 1, "every": 1, "contender": 1, "rocky": 1, "balboa": 1, "nice": 1, "jacket": 1, "tennis": 1, "tour": 1, "josh": 1, "fight": 1, "efficacy": 1, "language": 1, "overcome": 1, "lead": 1, "situation": 1, "smile": 1, "victory": 1, "calling": 1, "gathering": 1, "importance": 1, "connection": 1, "body": 1, "fire": 1, "passing": 1, "fortune": 1, "institution": 1, "person": 1, "merry": 1, "zero": 1, "sense": 1, "everlasting": 1, "legacy": 1, "break": 1, "button": 1, "excited": 1, "session": 1, "tradition": 1, "step": 1, "missing": 1, "happen": 1, "announce": 1, "produced": 1, "sideline": 1, "leg": 1, "together": 1, "pray": 1, "stream": 1, "case": 1, "push": 1, "shove": 1, "save": 1, "streaming": 1, "delighted": 1, "ala": 1, "polite": 1, "reminder": 1, "screen": 1, "roar": 1, "shave": 1, "baloo": 1, "promotion": 1, "spoken": 1, "whatever": 1, "place": 1, "birth": 1, "daughter": 1, "freak": 1, "boom": 1, "fantastic": 1, "launch": 1, "telling": 1, "success": 1, "fasting": 1, "wave": 1, "devoted": 1, "helping": 1, "teaching": 1, "oho": 1, "koi": 1, "storm": 1, "worker": 1, "drag": 1, "credit": 1, "go": 1, "build": 1, "momentum": 1, "spent": 1, "guess": 1, "tune": 1, "ist": 1, "paint": 1, "cheer": 1, "newspaper": 1, "jersey": 1, "fused": 1, "judge": 1, "touched": 1, "promise": 1, "wali": 1, "miss": 1, "register": 1, "end": 1, "stree": 1, "analyst": 1, "coz": 1, "said": 1, "information": 1, "professional": 1, "expect": 1, "study": 1, "proclaiming": 1, "economics": 1, "embarrass": 1, "clap": 1, "growing": 1, "name": 1, "panther": 1, "adorable": 1, "write": 1, "author": 1, "answer": 1, "quirky": 1, "intimate": 1, "novel": 1, "dan": 1, "sire": 1, "sung": 1, "ram": 1, "thug": 1, "jordan": 1, "lie": 1, "hair": 1, "prince": 1, "duality": 1, "rishi": 1, "type": 1, "cover": 1, "sit": 1, "chat": 1, "carpet": 1, "preorder": 1, "tell": 1, "taking": 1, "streep": 1, "award": 1, "excellence": 1, "congratulatory": 1, "theta": 1, "lovely": 1, "meeting": 1, "resist": 1, "warn": 1, "aka": 1, "dancing": 1, "change": 1, "mane": 1, "tiff": 1, "net": 1, "performance": 1, "food": 1, "heartbreak": 1, "august": 1, "desire": 1, "kit": 1, "spread": 1, "awareness": 1, "entry": 1, "arsenal": 1, "donate": 1, "maximum": 1, "phase": 1, "distributed": 1, "lyrical": 1, "student": 1, "concern": 1, "independence": 1, "period": 1, "voice": 1, "air": 1, "venture": 1, "niece": 1, "model": 1, "move": 1, "dance": 1, "ask": 1, "decision": 1, "drop": 1, "affected": 1, "manager": 1, "unending": 1, "dop": 1, "rab": 1, "awkward": 1, "audio": 1, "outdoor": 1, "came": 1, "stuff": 1, "gon": 1, "triple": 1, "lazy": 1, "cap": 1, "inspiring": 1, "leaf": 1, "lump": 1, "throat": 1, "waiting": 1, "explode": 1, "date": 1, "fought": 1, "pay": 1, "wasabi": 1, "bill": 1, "laughing": 1, "slip": 1, "refrain": 1, "intent": 1, "fly": 1, "disappoint": 1, "karo": 1, "hum": 1, "sab": 1, "turn": 1, "laughter": 1, "worked": 1, "entertaining": 1, "hence": 1, "silence": 1, "gold": 1, "level": 1, "da": 1, "beat": 1, "foot": 1, "evil": 1, "dare": 1, "crazy": 1, "brazil": 1, "sadly": 1, "gaby": 1, "possible": 1, "mouth": 1, "shut": 1, "eat": 1, "junk": 1, "beast": 1, "doubt": 1, "conversation": 1, "keeping": 1, "tone": 1, "convince": 1, "sure": 1, "defense": 1, "wrote": 1, "trouble": 1, "ever": 1, "tagged": 1, "mail": 1, "surely": 1, "discretion": 1, "cue": 1, "slim": 1, "unbelievable": 1, "insane": 1, "typical": 1, "faith": 1, "usual": 1, "pushing": 1, "russia": 1, "immense": 1, "effort": 1, "attract": 1, "classified": 1, "priority": 1, "community": 1, "association": 1, "decided": 1, "beating": 1, "hind": 1, "zombie": 1, "bump": 1}}